hamidshah/__init__.py
test_package/__init__.py
hamidshah-0.0.1.dist-info/LICENSE
hamidshah-0.0.1.dist-info/METADATA
hamidshah-0.0.1.dist-info/WHEEL
hamidshah-0.0.1.dist-info/top_level.txt
hamidshah-0.0.1.dist-info/RECORD
