Metadata-Version: 2.1
Name: hamidshah
Version: 0.0.1
Summary: A sample hamidshah
Home-page: https://github.com/gituser/hamidshah
Author: Hamidreza
Author-email: hshahzamanian@gmail.com
License: MIT
Requires-Python: >=3.8
License-File: LICENSE
